recipes/__init__.py
recipes/sync_recipe_utils.py
recipes/sync_recipes.py
solvebio/__init__.py
solvebio/__main__.py
solvebio/annotate.py
solvebio/auth.py
solvebio/client.py
solvebio/errors.py
solvebio/global_search.py
solvebio/help.py
solvebio/query.py
solvebio/version.py
solvebio/cli/__init__.py
solvebio/cli/auth.py
solvebio/cli/credentials.py
solvebio/cli/data.py
solvebio/cli/ipython.py
solvebio/cli/ipython_init.py
solvebio/cli/main.py
solvebio/cli/tutorial.md
solvebio/cli/tutorial.py
solvebio/contrib/__init__.py
solvebio/contrib/dash/README.md
solvebio/contrib/dash/__init__.py
solvebio/contrib/dash/login.js
solvebio/contrib/dash/oauth-redirect.js
solvebio/contrib/dash/solvebio_auth.py
solvebio/contrib/dash/solvebio_dash.py
solvebio/contrib/dash/usage.py
solvebio/contrib/dash/js/README.md
solvebio/contrib/dash/js/node_modules/abbrev/README.md
solvebio/contrib/dash/js/node_modules/accepts/HISTORY.md
solvebio/contrib/dash/js/node_modules/accepts/README.md
solvebio/contrib/dash/js/node_modules/acorn/CHANGELOG.md
solvebio/contrib/dash/js/node_modules/acorn/README.md
solvebio/contrib/dash/js/node_modules/acorn-dynamic-import/CHANGELOG.md
solvebio/contrib/dash/js/node_modules/acorn-dynamic-import/README.md
solvebio/contrib/dash/js/node_modules/acorn-dynamic-import/node_modules/acorn/CHANGELOG.md
solvebio/contrib/dash/js/node_modules/acorn-dynamic-import/node_modules/acorn/README.md
solvebio/contrib/dash/js/node_modules/acorn-jsx/README.md
solvebio/contrib/dash/js/node_modules/acorn-jsx/node_modules/acorn/CHANGELOG.md
solvebio/contrib/dash/js/node_modules/acorn-jsx/node_modules/acorn/README.md
solvebio/contrib/dash/js/node_modules/ajv/README.md
solvebio/contrib/dash/js/node_modules/ajv/lib/dotjs/README.md
solvebio/contrib/dash/js/node_modules/ajv-keywords/README.md
solvebio/contrib/dash/js/node_modules/ajv-keywords/keywords/dotjs/README.md
solvebio/contrib/dash/js/node_modules/align-text/README.md
solvebio/contrib/dash/js/node_modules/alphanum-sort/README.md
solvebio/contrib/dash/js/node_modules/hosted-git-info/README.md
solvebio-2.32.0.dist-info/licenses/AUTHORS
solvebio-2.32.0.dist-info/licenses/LICENSE
solvebio-2.32.0.dist-info/METADATA
solvebio-2.32.0.dist-info/WHEEL
solvebio-2.32.0.dist-info/entry_points.txt
solvebio-2.32.0.dist-info/top_level.txt
solvebio-2.32.0.dist-info/RECORD
