Metadata-Version: 2.4
Name: solvebio
Version: 2.32.0
Summary: The SolveBio Python client
Home-page: https://github.com/solvebio/solvebio-python
Author: Solve, Inc.
Author-email: contact@solvebio.com
Platform: any
Classifier: Intended Audience :: Science/Research
Classifier: Operating System :: OS Independent
Classifier: Programming Language :: Python
Classifier: Topic :: Software Development :: Libraries :: Python Modules
Classifier: Topic :: Scientific/Engineering :: Bio-Informatics
Requires-Python: >=3.8
License-File: LICENSE
License-File: AUTHORS
Requires-Dist: six
Requires-Dist: pyprind
Requires-Dist: requests>=2.0.0
Provides-Extra: recipes
Requires-Dist: pyyaml==5.3.1; extra == "recipes"
Requires-Dist: click==7.1.2; extra == "recipes"
Requires-Dist: ruamel.yaml==0.16.12; extra == "recipes"
Dynamic: author
Dynamic: author-email
Dynamic: classifier
Dynamic: description
Dynamic: description-content-type
Dynamic: home-page
Dynamic: license-file
Dynamic: platform
Dynamic: provides-extra
Dynamic: requires-dist
Dynamic: requires-python
Dynamic: summary
